helpme171/__init__.py
helpme171/demod.py
helpme171/submods2/mod2.py
helpme171-0.0.13.dist-info/LICENSE
helpme171-0.0.13.dist-info/METADATA
helpme171-0.0.13.dist-info/WHEEL
helpme171-0.0.13.dist-info/top_level.txt
helpme171-0.0.13.dist-info/RECORD
