Metadata-Version: 2.1
Name: helpme171
Version: 0.0.13
Summary: A package with functions I use often.
Classifier: Programming Language :: Python :: 3
Classifier: License :: OSI Approved :: MIT License
Classifier: Operating System :: OS Independent
Requires-Python: >=3.9
License-File: LICENSE
Requires-Dist: numpy >=1.22.0
Requires-Dist: ipykernel >=6.27.1
